[
  {
    "alert_id": 0,
    "timestamp": 1764762580.032512,
    "signature_text": "SURICATA Ethertype unknown",
    "category_text": "Generic Protocol Command Decode",
    "src_ip": "",
    "dest_ip": "",
    "proto": "",
    "app_proto": "",
    "src_port": 0,
    "dest_port": 0,
    "signature_length": 26,
    "signature_word_count": 3,
    "threat_malware": 0,
    "threat_exploit": 0,
    "threat_scan": 0,
    "threat_dos": 0,
    "threat_botnet": 0,
    "threat_suspicious": 0,
    "flow_direction": ""
  },
  {
    "alert_id": 0,
    "timestamp": 1764762580.800544,
    "signature_text": "SURICATA Ethertype unknown",
    "category_text": "Generic Protocol Command Decode",
    "src_ip": "",
    "dest_ip": "",
    "proto": "",
    "app_proto": "",
    "src_port": 0,
    "dest_port": 0,
    "signature_length": 26,
    "signature_word_count": 3,
    "threat_malware": 0,
    "threat_exploit": 0,
    "threat_scan": 0,
    "threat_dos": 0,
    "threat_botnet": 0,
    "threat_suspicious": 0,
    "flow_direction": ""
  },
  {
    "alert_id": 0,
    "timestamp": 1764762581.817989,
    "signature_text": "SURICATA Ethertype unknown",
    "category_text": "Generic Protocol Command Decode",
    "src_ip": "",
    "dest_ip": "",
    "proto": "",
    "app_proto": "",
    "src_port": 0,
    "dest_port": 0,
    "signature_length": 26,
    "signature_word_count": 3,
    "threat_malware": 0,
    "threat_exploit": 0,
    "threat_scan": 0,
    "threat_dos": 0,
    "threat_botnet": 0,
    "threat_suspicious": 0,
    "flow_direction": ""
  },
  {
    "alert_id": 0,
    "timestamp": 1764762583.793817,
    "signature_text": "SURICATA Ethertype unknown",
    "category_text": "Generic Protocol Command Decode",
    "src_ip": "",
    "dest_ip": "",
    "proto": "",
    "app_proto": "",
    "src_port": 0,
    "dest_port": 0,
    "signature_length": 26,
    "signature_word_count": 3,
    "threat_malware": 0,
    "threat_exploit": 0,
    "threat_scan": 0,
    "threat_dos": 0,
    "threat_botnet": 0,
    "threat_suspicious": 0,
    "flow_direction": ""
  },
  {
    "alert_id": 1176008051807629,
    "timestamp": 1764762584.008697,
    "signature_text": "SURICATA STREAM ESTABLISHED SYNACK resend with different ACK",
    "category_text": "Generic Protocol Command Decode",
    "src_ip": "116.205.147.74",
    "dest_ip": "10.80.9.61",
    "proto": "TCP",
    "app_proto": "tls",
    "src_port": 443,
    "dest_port": 54002,
    "signature_length": 60,
    "signature_word_count": 8,
    "threat_malware": 0,
    "threat_exploit": 0,
    "threat_scan": 0,
    "threat_dos": 0,
    "threat_botnet": 0,
    "threat_suspicious": 0,
    "flow_direction": "to_client"
  },
  {
    "alert_id": 0,
    "timestamp": 1764762585.793303,
    "signature_text": "SURICATA Ethertype unknown",
    "category_text": "Generic Protocol Command Decode",
    "src_ip": "",
    "dest_ip": "",
    "proto": "",
    "app_proto": "",
    "src_port": 0,
    "dest_port": 0,
    "signature_length": 26,
    "signature_word_count": 3,
    "threat_malware": 0,
    "threat_exploit": 0,
    "threat_scan": 0,
    "threat_dos": 0,
    "threat_botnet": 0,
    "threat_suspicious": 0,
    "flow_direction": ""
  },
  {
    "alert_id": 1346324558550207,
    "timestamp": 1764762586.895109,
    "signature_text": "SURICATA STREAM excessive retransmissions",
    "category_text": "Generic Protocol Command Decode",
    "src_ip": "10.80.9.61",
    "dest_ip": "157.240.195.3",
    "proto": "TCP",
    "app_proto": "tls",
    "src_port": 62687,
    "dest_port": 443,
    "signature_length": 41,
    "signature_word_count": 4,
    "threat_malware": 0,
    "threat_exploit": 0,
    "threat_scan": 0,
    "threat_dos": 0,
    "threat_botnet": 0,
    "threat_suspicious": 0,
    "flow_direction": "to_server"
  },
  {
    "alert_id": 0,
    "timestamp": 1764762587.792315,
    "signature_text": "SURICATA Ethertype unknown",
    "category_text": "Generic Protocol Command Decode",
    "src_ip": "",
    "dest_ip": "",
    "proto": "",
    "app_proto": "",
    "src_port": 0,
    "dest_port": 0,
    "signature_length": 26,
    "signature_word_count": 3,
    "threat_malware": 0,
    "threat_exploit": 0,
    "threat_scan": 0,
    "threat_dos": 0,
    "threat_botnet": 0,
    "threat_suspicious": 0,
    "flow_direction": ""
  },
  {
    "alert_id": 0,
    "timestamp": 1764762589.794903,
    "signature_text": "SURICATA Ethertype unknown",
    "category_text": "Generic Protocol Command Decode",
    "src_ip": "",
    "dest_ip": "",
    "proto": "",
    "app_proto": "",
    "src_port": 0,
    "dest_port": 0,
    "signature_length": 26,
    "signature_word_count": 3,
    "threat_malware": 0,
    "threat_exploit": 0,
    "threat_scan": 0,
    "threat_dos": 0,
    "threat_botnet": 0,
    "threat_suspicious": 0,
    "flow_direction": ""
  },
  {
    "alert_id": 0,
    "timestamp": 1764762590.032127,
    "signature_text": "SURICATA Ethertype unknown",
    "category_text": "Generic Protocol Command Decode",
    "src_ip": "",
    "dest_ip": "",
    "proto": "",
    "app_proto": "",
    "src_port": 0,
    "dest_port": 0,
    "signature_length": 26,
    "signature_word_count": 3,
    "threat_malware": 0,
    "threat_exploit": 0,
    "threat_scan": 0,
    "threat_dos": 0,
    "threat_botnet": 0,
    "threat_suspicious": 0,
    "flow_direction": ""
  },
  {
    "alert_id": 0,
    "timestamp": 1764762591.794636,
    "signature_text": "SURICATA Ethertype unknown",
    "category_text": "Generic Protocol Command Decode",
    "src_ip": "",
    "dest_ip": "",
    "proto": "",
    "app_proto": "",
    "src_port": 0,
    "dest_port": 0,
    "signature_length": 26,
    "signature_word_count": 3,
    "threat_malware": 0,
    "threat_exploit": 0,
    "threat_scan": 0,
    "threat_dos": 0,
    "threat_botnet": 0,
    "threat_suspicious": 0,
    "flow_direction": ""
  },
  {
    "alert_id": 0,
    "timestamp": 1764762593.793658,
    "signature_text": "SURICATA Ethertype unknown",
    "category_text": "Generic Protocol Command Decode",
    "src_ip": "",
    "dest_ip": "",
    "proto": "",
    "app_proto": "",
    "src_port": 0,
    "dest_port": 0,
    "signature_length": 26,
    "signature_word_count": 3,
    "threat_malware": 0,
    "threat_exploit": 0,
    "threat_scan": 0,
    "threat_dos": 0,
    "threat_botnet": 0,
    "threat_suspicious": 0,
    "flow_direction": ""
  },
  {
    "alert_id": 562726012389902,
    "timestamp": 1764762593.920901,
    "signature_text": "ET INFO Windows Update P2P Activity",
    "category_text": "Not Suspicious Traffic",
    "src_ip": "10.80.9.61",
    "dest_ip": "10.63.0.67",
    "proto": "TCP",
    "app_proto": "",
    "src_port": 54004,
    "dest_port": 7680,
    "signature_length": 35,
    "signature_word_count": 6,
    "threat_malware": 0,
    "threat_exploit": 0,
    "threat_scan": 0,
    "threat_dos": 0,
    "threat_botnet": 0,
    "threat_suspicious": 0,
    "flow_direction": "to_server"
  },
  {
    "alert_id": 0,
    "timestamp": 1764762595.791613,
    "signature_text": "SURICATA Ethertype unknown",
    "category_text": "Generic Protocol Command Decode",
    "src_ip": "",
    "dest_ip": "",
    "proto": "",
    "app_proto": "",
    "src_port": 0,
    "dest_port": 0,
    "signature_length": 26,
    "signature_word_count": 3,
    "threat_malware": 0,
    "threat_exploit": 0,
    "threat_scan": 0,
    "threat_dos": 0,
    "threat_botnet": 0,
    "threat_suspicious": 0,
    "flow_direction": ""
  },
  {
    "alert_id": 0,
    "timestamp": 1764762597.790494,
    "signature_text": "SURICATA Ethertype unknown",
    "category_text": "Generic Protocol Command Decode",
    "src_ip": "",
    "dest_ip": "",
    "proto": "",
    "app_proto": "",
    "src_port": 0,
    "dest_port": 0,
    "signature_length": 26,
    "signature_word_count": 3,
    "threat_malware": 0,
    "threat_exploit": 0,
    "threat_scan": 0,
    "threat_dos": 0,
    "threat_botnet": 0,
    "threat_suspicious": 0,
    "flow_direction": ""
  },
  {
    "alert_id": 0,
    "timestamp": 1764762598.549551,
    "signature_text": "SURICATA Ethertype unknown",
    "category_text": "Generic Protocol Command Decode",
    "src_ip": "",
    "dest_ip": "",
    "proto": "",
    "app_proto": "",
    "src_port": 0,
    "dest_port": 0,
    "signature_length": 26,
    "signature_word_count": 3,
    "threat_malware": 0,
    "threat_exploit": 0,
    "threat_scan": 0,
    "threat_dos": 0,
    "threat_botnet": 0,
    "threat_suspicious": 0,
    "flow_direction": ""
  },
  {
    "alert_id": 0,
    "timestamp": 1764762598.549554,
    "signature_text": "SURICATA Ethertype unknown",
    "category_text": "Generic Protocol Command Decode",
    "src_ip": "",
    "dest_ip": "",
    "proto": "",
    "app_proto": "",
    "src_port": 0,
    "dest_port": 0,
    "signature_length": 26,
    "signature_word_count": 3,
    "threat_malware": 0,
    "threat_exploit": 0,
    "threat_scan": 0,
    "threat_dos": 0,
    "threat_botnet": 0,
    "threat_suspicious": 0,
    "flow_direction": ""
  },
  {
    "alert_id": 859071113215943,
    "timestamp": 1764762598.834217,
    "signature_text": "GPL ATTACK_RESPONSE id check returned root",
    "category_text": "Potentially Bad Traffic",
    "src_ip": "18.66.122.97",
    "dest_ip": "10.80.10.147",
    "proto": "TCP",
    "app_proto": "http",
    "src_port": 80,
    "dest_port": 43972,
    "signature_length": 42,
    "signature_word_count": 6,
    "threat_malware": 0,
    "threat_exploit": 0,
    "threat_scan": 0,
    "threat_dos": 0,
    "threat_botnet": 0,
    "threat_suspicious": 0,
    "flow_direction": "to_client"
  },
  {
    "alert_id": 0,
    "timestamp": 1764762599.790369,
    "signature_text": "SURICATA Ethertype unknown",
    "category_text": "Generic Protocol Command Decode",
    "src_ip": "",
    "dest_ip": "",
    "proto": "",
    "app_proto": "",
    "src_port": 0,
    "dest_port": 0,
    "signature_length": 26,
    "signature_word_count": 3,
    "threat_malware": 0,
    "threat_exploit": 0,
    "threat_scan": 0,
    "threat_dos": 0,
    "threat_botnet": 0,
    "threat_suspicious": 0,
    "flow_direction": ""
  },
  {
    "alert_id": 0,
    "timestamp": 1764762600.031736,
    "signature_text": "SURICATA Ethertype unknown",
    "category_text": "Generic Protocol Command Decode",
    "src_ip": "",
    "dest_ip": "",
    "proto": "",
    "app_proto": "",
    "src_port": 0,
    "dest_port": 0,
    "signature_length": 26,
    "signature_word_count": 3,
    "threat_malware": 0,
    "threat_exploit": 0,
    "threat_scan": 0,
    "threat_dos": 0,
    "threat_botnet": 0,
    "threat_suspicious": 0,
    "flow_direction": ""
  },
  {
    "alert_id": 0,
    "timestamp": 1764762601.790743,
    "signature_text": "SURICATA Ethertype unknown",
    "category_text": "Generic Protocol Command Decode",
    "src_ip": "",
    "dest_ip": "",
    "proto": "",
    "app_proto": "",
    "src_port": 0,
    "dest_port": 0,
    "signature_length": 26,
    "signature_word_count": 3,
    "threat_malware": 0,
    "threat_exploit": 0,
    "threat_scan": 0,
    "threat_dos": 0,
    "threat_botnet": 0,
    "threat_suspicious": 0,
    "flow_direction": ""
  },
  {
    "alert_id": 0,
    "timestamp": 1764762603.790497,
    "signature_text": "SURICATA Ethertype unknown",
    "category_text": "Generic Protocol Command Decode",
    "src_ip": "",
    "dest_ip": "",
    "proto": "",
    "app_proto": "",
    "src_port": 0,
    "dest_port": 0,
    "signature_length": 26,
    "signature_word_count": 3,
    "threat_malware": 0,
    "threat_exploit": 0,
    "threat_scan": 0,
    "threat_dos": 0,
    "threat_botnet": 0,
    "threat_suspicious": 0,
    "flow_direction": ""
  },
  {
    "alert_id": 0,
    "timestamp": 1764762605.794558,
    "signature_text": "SURICATA Ethertype unknown",
    "category_text": "Generic Protocol Command Decode",
    "src_ip": "",
    "dest_ip": "",
    "proto": "",
    "app_proto": "",
    "src_port": 0,
    "dest_port": 0,
    "signature_length": 26,
    "signature_word_count": 3,
    "threat_malware": 0,
    "threat_exploit": 0,
    "threat_scan": 0,
    "threat_dos": 0,
    "threat_botnet": 0,
    "threat_suspicious": 0,
    "flow_direction": ""
  },
  {
    "alert_id": 0,
    "timestamp": 1764762607.814386,
    "signature_text": "SURICATA Ethertype unknown",
    "category_text": "Generic Protocol Command Decode",
    "src_ip": "",
    "dest_ip": "",
    "proto": "",
    "app_proto": "",
    "src_port": 0,
    "dest_port": 0,
    "signature_length": 26,
    "signature_word_count": 3,
    "threat_malware": 0,
    "threat_exploit": 0,
    "threat_scan": 0,
    "threat_dos": 0,
    "threat_botnet": 0,
    "threat_suspicious": 0,
    "flow_direction": ""
  },
  {
    "alert_id": 0,
    "timestamp": 1764762609.792379,
    "signature_text": "SURICATA Ethertype unknown",
    "category_text": "Generic Protocol Command Decode",
    "src_ip": "",
    "dest_ip": "",
    "proto": "",
    "app_proto": "",
    "src_port": 0,
    "dest_port": 0,
    "signature_length": 26,
    "signature_word_count": 3,
    "threat_malware": 0,
    "threat_exploit": 0,
    "threat_scan": 0,
    "threat_dos": 0,
    "threat_botnet": 0,
    "threat_suspicious": 0,
    "flow_direction": ""
  },
  {
    "alert_id": 0,
    "timestamp": 1764762610.031934,
    "signature_text": "SURICATA Ethertype unknown",
    "category_text": "Generic Protocol Command Decode",
    "src_ip": "",
    "dest_ip": "",
    "proto": "",
    "app_proto": "",
    "src_port": 0,
    "dest_port": 0,
    "signature_length": 26,
    "signature_word_count": 3,
    "threat_malware": 0,
    "threat_exploit": 0,
    "threat_scan": 0,
    "threat_dos": 0,
    "threat_botnet": 0,
    "threat_suspicious": 0,
    "flow_direction": ""
  },
  {
    "alert_id": 0,
    "timestamp": 1764762610.789943,
    "signature_text": "SURICATA Ethertype unknown",
    "category_text": "Generic Protocol Command Decode",
    "src_ip": "",
    "dest_ip": "",
    "proto": "",
    "app_proto": "",
    "src_port": 0,
    "dest_port": 0,
    "signature_length": 26,
    "signature_word_count": 3,
    "threat_malware": 0,
    "threat_exploit": 0,
    "threat_scan": 0,
    "threat_dos": 0,
    "threat_botnet": 0,
    "threat_suspicious": 0,
    "flow_direction": ""
  },
  {
    "alert_id": 0,
    "timestamp": 1764762611.790972,
    "signature_text": "SURICATA Ethertype unknown",
    "category_text": "Generic Protocol Command Decode",
    "src_ip": "",
    "dest_ip": "",
    "proto": "",
    "app_proto": "",
    "src_port": 0,
    "dest_port": 0,
    "signature_length": 26,
    "signature_word_count": 3,
    "threat_malware": 0,
    "threat_exploit": 0,
    "threat_scan": 0,
    "threat_dos": 0,
    "threat_botnet": 0,
    "threat_suspicious": 0,
    "flow_direction": ""
  },
  {
    "alert_id": 0,
    "timestamp": 1764762613.790251,
    "signature_text": "SURICATA Ethertype unknown",
    "category_text": "Generic Protocol Command Decode",
    "src_ip": "",
    "dest_ip": "",
    "proto": "",
    "app_proto": "",
    "src_port": 0,
    "dest_port": 0,
    "signature_length": 26,
    "signature_word_count": 3,
    "threat_malware": 0,
    "threat_exploit": 0,
    "threat_scan": 0,
    "threat_dos": 0,
    "threat_botnet": 0,
    "threat_suspicious": 0,
    "flow_direction": ""
  },
  {
    "alert_id": 0,
    "timestamp": 1764762615.794412,
    "signature_text": "SURICATA Ethertype unknown",
    "category_text": "Generic Protocol Command Decode",
    "src_ip": "",
    "dest_ip": "",
    "proto": "",
    "app_proto": "",
    "src_port": 0,
    "dest_port": 0,
    "signature_length": 26,
    "signature_word_count": 3,
    "threat_malware": 0,
    "threat_exploit": 0,
    "threat_scan": 0,
    "threat_dos": 0,
    "threat_botnet": 0,
    "threat_suspicious": 0,
    "flow_direction": ""
  },
  {
    "alert_id": 0,
    "timestamp": 1764762616.795181,
    "signature_text": "SURICATA Ethertype unknown",
    "category_text": "Generic Protocol Command Decode",
    "src_ip": "",
    "dest_ip": "",
    "proto": "",
    "app_proto": "",
    "src_port": 0,
    "dest_port": 0,
    "signature_length": 26,
    "signature_word_count": 3,
    "threat_malware": 0,
    "threat_exploit": 0,
    "threat_scan": 0,
    "threat_dos": 0,
    "threat_botnet": 0,
    "threat_suspicious": 0,
    "flow_direction": ""
  },
  {
    "alert_id": 0,
    "timestamp": 1764762617.795607,
    "signature_text": "SURICATA Ethertype unknown",
    "category_text": "Generic Protocol Command Decode",
    "src_ip": "",
    "dest_ip": "",
    "proto": "",
    "app_proto": "",
    "src_port": 0,
    "dest_port": 0,
    "signature_length": 26,
    "signature_word_count": 3,
    "threat_malware": 0,
    "threat_exploit": 0,
    "threat_scan": 0,
    "threat_dos": 0,
    "threat_botnet": 0,
    "threat_suspicious": 0,
    "flow_direction": ""
  },
  {
    "alert_id": 0,
    "timestamp": 1764762618.797993,
    "signature_text": "SURICATA Ethertype unknown",
    "category_text": "Generic Protocol Command Decode",
    "src_ip": "",
    "dest_ip": "",
    "proto": "",
    "app_proto": "",
    "src_port": 0,
    "dest_port": 0,
    "signature_length": 26,
    "signature_word_count": 3,
    "threat_malware": 0,
    "threat_exploit": 0,
    "threat_scan": 0,
    "threat_dos": 0,
    "threat_botnet": 0,
    "threat_suspicious": 0,
    "flow_direction": ""
  },
  {
    "alert_id": 0,
    "timestamp": 1764762620.061069,
    "signature_text": "SURICATA Ethertype unknown",
    "category_text": "Generic Protocol Command Decode",
    "src_ip": "",
    "dest_ip": "",
    "proto": "",
    "app_proto": "",
    "src_port": 0,
    "dest_port": 0,
    "signature_length": 26,
    "signature_word_count": 3,
    "threat_malware": 0,
    "threat_exploit": 0,
    "threat_scan": 0,
    "threat_dos": 0,
    "threat_botnet": 0,
    "threat_suspicious": 0,
    "flow_direction": ""
  },
  {
    "alert_id": 0,
    "timestamp": 1764762620.790673,
    "signature_text": "SURICATA Ethertype unknown",
    "category_text": "Generic Protocol Command Decode",
    "src_ip": "",
    "dest_ip": "",
    "proto": "",
    "app_proto": "",
    "src_port": 0,
    "dest_port": 0,
    "signature_length": 26,
    "signature_word_count": 3,
    "threat_malware": 0,
    "threat_exploit": 0,
    "threat_scan": 0,
    "threat_dos": 0,
    "threat_botnet": 0,
    "threat_suspicious": 0,
    "flow_direction": ""
  },
  {
    "alert_id": 0,
    "timestamp": 1764762622.790259,
    "signature_text": "SURICATA Ethertype unknown",
    "category_text": "Generic Protocol Command Decode",
    "src_ip": "",
    "dest_ip": "",
    "proto": "",
    "app_proto": "",
    "src_port": 0,
    "dest_port": 0,
    "signature_length": 26,
    "signature_word_count": 3,
    "threat_malware": 0,
    "threat_exploit": 0,
    "threat_scan": 0,
    "threat_dos": 0,
    "threat_botnet": 0,
    "threat_suspicious": 0,
    "flow_direction": ""
  },
  {
    "alert_id": 1092410621987412,
    "timestamp": 1764762622.80086,
    "signature_text": "GPL ATTACK_RESPONSE id check returned root",
    "category_text": "Potentially Bad Traffic",
    "src_ip": "18.66.122.97",
    "dest_ip": "10.80.10.147",
    "proto": "TCP",
    "app_proto": "http",
    "src_port": 80,
    "dest_port": 45202,
    "signature_length": 42,
    "signature_word_count": 6,
    "threat_malware": 0,
    "threat_exploit": 0,
    "threat_scan": 0,
    "threat_dos": 0,
    "threat_botnet": 0,
    "threat_suspicious": 0,
    "flow_direction": "to_client"
  },
  {
    "alert_id": 0,
    "timestamp": 1764762624.790685,
    "signature_text": "SURICATA Ethertype unknown",
    "category_text": "Generic Protocol Command Decode",
    "src_ip": "",
    "dest_ip": "",
    "proto": "",
    "app_proto": "",
    "src_port": 0,
    "dest_port": 0,
    "signature_length": 26,
    "signature_word_count": 3,
    "threat_malware": 0,
    "threat_exploit": 0,
    "threat_scan": 0,
    "threat_dos": 0,
    "threat_botnet": 0,
    "threat_suspicious": 0,
    "flow_direction": ""
  },
  {
    "alert_id": 0,
    "timestamp": 1764762626.794197,
    "signature_text": "SURICATA Ethertype unknown",
    "category_text": "Generic Protocol Command Decode",
    "src_ip": "",
    "dest_ip": "",
    "proto": "",
    "app_proto": "",
    "src_port": 0,
    "dest_port": 0,
    "signature_length": 26,
    "signature_word_count": 3,
    "threat_malware": 0,
    "threat_exploit": 0,
    "threat_scan": 0,
    "threat_dos": 0,
    "threat_botnet": 0,
    "threat_suspicious": 0,
    "flow_direction": ""
  },
  {
    "alert_id": 0,
    "timestamp": 1764762628.549144,
    "signature_text": "SURICATA Ethertype unknown",
    "category_text": "Generic Protocol Command Decode",
    "src_ip": "",
    "dest_ip": "",
    "proto": "",
    "app_proto": "",
    "src_port": 0,
    "dest_port": 0,
    "signature_length": 26,
    "signature_word_count": 3,
    "threat_malware": 0,
    "threat_exploit": 0,
    "threat_scan": 0,
    "threat_dos": 0,
    "threat_botnet": 0,
    "threat_suspicious": 0,
    "flow_direction": ""
  },
  {
    "alert_id": 0,
    "timestamp": 1764762628.549146,
    "signature_text": "SURICATA Ethertype unknown",
    "category_text": "Generic Protocol Command Decode",
    "src_ip": "",
    "dest_ip": "",
    "proto": "",
    "app_proto": "",
    "src_port": 0,
    "dest_port": 0,
    "signature_length": 26,
    "signature_word_count": 3,
    "threat_malware": 0,
    "threat_exploit": 0,
    "threat_scan": 0,
    "threat_dos": 0,
    "threat_botnet": 0,
    "threat_suspicious": 0,
    "flow_direction": ""
  },
  {
    "alert_id": 0,
    "timestamp": 1764762628.790445,
    "signature_text": "SURICATA Ethertype unknown",
    "category_text": "Generic Protocol Command Decode",
    "src_ip": "",
    "dest_ip": "",
    "proto": "",
    "app_proto": "",
    "src_port": 0,
    "dest_port": 0,
    "signature_length": 26,
    "signature_word_count": 3,
    "threat_malware": 0,
    "threat_exploit": 0,
    "threat_scan": 0,
    "threat_dos": 0,
    "threat_botnet": 0,
    "threat_suspicious": 0,
    "flow_direction": ""
  },
  {
    "alert_id": 0,
    "timestamp": 1764762630.063263,
    "signature_text": "SURICATA Ethertype unknown",
    "category_text": "Generic Protocol Command Decode",
    "src_ip": "",
    "dest_ip": "",
    "proto": "",
    "app_proto": "",
    "src_port": 0,
    "dest_port": 0,
    "signature_length": 26,
    "signature_word_count": 3,
    "threat_malware": 0,
    "threat_exploit": 0,
    "threat_scan": 0,
    "threat_dos": 0,
    "threat_botnet": 0,
    "threat_suspicious": 0,
    "flow_direction": ""
  },
  {
    "alert_id": 0,
    "timestamp": 1764762630.790379,
    "signature_text": "SURICATA Ethertype unknown",
    "category_text": "Generic Protocol Command Decode",
    "src_ip": "",
    "dest_ip": "",
    "proto": "",
    "app_proto": "",
    "src_port": 0,
    "dest_port": 0,
    "signature_length": 26,
    "signature_word_count": 3,
    "threat_malware": 0,
    "threat_exploit": 0,
    "threat_scan": 0,
    "threat_dos": 0,
    "threat_botnet": 0,
    "threat_suspicious": 0,
    "flow_direction": ""
  },
  {
    "alert_id": 0,
    "timestamp": 1764762631.790119,
    "signature_text": "SURICATA Ethertype unknown",
    "category_text": "Generic Protocol Command Decode",
    "src_ip": "",
    "dest_ip": "",
    "proto": "",
    "app_proto": "",
    "src_port": 0,
    "dest_port": 0,
    "signature_length": 26,
    "signature_word_count": 3,
    "threat_malware": 0,
    "threat_exploit": 0,
    "threat_scan": 0,
    "threat_dos": 0,
    "threat_botnet": 0,
    "threat_suspicious": 0,
    "flow_direction": ""
  },
  {
    "alert_id": 0,
    "timestamp": 1764762632.790288,
    "signature_text": "SURICATA Ethertype unknown",
    "category_text": "Generic Protocol Command Decode",
    "src_ip": "",
    "dest_ip": "",
    "proto": "",
    "app_proto": "",
    "src_port": 0,
    "dest_port": 0,
    "signature_length": 26,
    "signature_word_count": 3,
    "threat_malware": 0,
    "threat_exploit": 0,
    "threat_scan": 0,
    "threat_dos": 0,
    "threat_botnet": 0,
    "threat_suspicious": 0,
    "flow_direction": ""
  },
  {
    "alert_id": 0,
    "timestamp": 1764762633.790479,
    "signature_text": "SURICATA Ethertype unknown",
    "category_text": "Generic Protocol Command Decode",
    "src_ip": "",
    "dest_ip": "",
    "proto": "",
    "app_proto": "",
    "src_port": 0,
    "dest_port": 0,
    "signature_length": 26,
    "signature_word_count": 3,
    "threat_malware": 0,
    "threat_exploit": 0,
    "threat_scan": 0,
    "threat_dos": 0,
    "threat_botnet": 0,
    "threat_suspicious": 0,
    "flow_direction": ""
  },
  {
    "alert_id": 0,
    "timestamp": 1764762634.796863,
    "signature_text": "SURICATA Ethertype unknown",
    "category_text": "Generic Protocol Command Decode",
    "src_ip": "",
    "dest_ip": "",
    "proto": "",
    "app_proto": "",
    "src_port": 0,
    "dest_port": 0,
    "signature_length": 26,
    "signature_word_count": 3,
    "threat_malware": 0,
    "threat_exploit": 0,
    "threat_scan": 0,
    "threat_dos": 0,
    "threat_botnet": 0,
    "threat_suspicious": 0,
    "flow_direction": ""
  },
  {
    "alert_id": 0,
    "timestamp": 1764762636.794781,
    "signature_text": "SURICATA Ethertype unknown",
    "category_text": "Generic Protocol Command Decode",
    "src_ip": "",
    "dest_ip": "",
    "proto": "",
    "app_proto": "",
    "src_port": 0,
    "dest_port": 0,
    "signature_length": 26,
    "signature_word_count": 3,
    "threat_malware": 0,
    "threat_exploit": 0,
    "threat_scan": 0,
    "threat_dos": 0,
    "threat_botnet": 0,
    "threat_suspicious": 0,
    "flow_direction": ""
  },
  {
    "alert_id": 0,
    "timestamp": 1764762637.078094,
    "signature_text": "SURICATA Ethertype unknown",
    "category_text": "Generic Protocol Command Decode",
    "src_ip": "",
    "dest_ip": "",
    "proto": "",
    "app_proto": "",
    "src_port": 0,
    "dest_port": 0,
    "signature_length": 26,
    "signature_word_count": 3,
    "threat_malware": 0,
    "threat_exploit": 0,
    "threat_scan": 0,
    "threat_dos": 0,
    "threat_botnet": 0,
    "threat_suspicious": 0,
    "flow_direction": ""
  },
  {
    "alert_id": 0,
    "timestamp": 1764762638.790774,
    "signature_text": "SURICATA Ethertype unknown",
    "category_text": "Generic Protocol Command Decode",
    "src_ip": "",
    "dest_ip": "",
    "proto": "",
    "app_proto": "",
    "src_port": 0,
    "dest_port": 0,
    "signature_length": 26,
    "signature_word_count": 3,
    "threat_malware": 0,
    "threat_exploit": 0,
    "threat_scan": 0,
    "threat_dos": 0,
    "threat_botnet": 0,
    "threat_suspicious": 0,
    "flow_direction": ""
  },
  {
    "alert_id": 0,
    "timestamp": 1764762640.063541,
    "signature_text": "SURICATA Ethertype unknown",
    "category_text": "Generic Protocol Command Decode",
    "src_ip": "",
    "dest_ip": "",
    "proto": "",
    "app_proto": "",
    "src_port": 0,
    "dest_port": 0,
    "signature_length": 26,
    "signature_word_count": 3,
    "threat_malware": 0,
    "threat_exploit": 0,
    "threat_scan": 0,
    "threat_dos": 0,
    "threat_botnet": 0,
    "threat_suspicious": 0,
    "flow_direction": ""
  },
  {
    "alert_id": 0,
    "timestamp": 1764762640.794567,
    "signature_text": "SURICATA Ethertype unknown",
    "category_text": "Generic Protocol Command Decode",
    "src_ip": "",
    "dest_ip": "",
    "proto": "",
    "app_proto": "",
    "src_port": 0,
    "dest_port": 0,
    "signature_length": 26,
    "signature_word_count": 3,
    "threat_malware": 0,
    "threat_exploit": 0,
    "threat_scan": 0,
    "threat_dos": 0,
    "threat_botnet": 0,
    "threat_suspicious": 0,
    "flow_direction": ""
  },
  {
    "alert_id": 0,
    "timestamp": 1764762642.790562,
    "signature_text": "SURICATA Ethertype unknown",
    "category_text": "Generic Protocol Command Decode",
    "src_ip": "",
    "dest_ip": "",
    "proto": "",
    "app_proto": "",
    "src_port": 0,
    "dest_port": 0,
    "signature_length": 26,
    "signature_word_count": 3,
    "threat_malware": 0,
    "threat_exploit": 0,
    "threat_scan": 0,
    "threat_dos": 0,
    "threat_botnet": 0,
    "threat_suspicious": 0,
    "flow_direction": ""
  },
  {
    "alert_id": 0,
    "timestamp": 1764762644.790528,
    "signature_text": "SURICATA Ethertype unknown",
    "category_text": "Generic Protocol Command Decode",
    "src_ip": "",
    "dest_ip": "",
    "proto": "",
    "app_proto": "",
    "src_port": 0,
    "dest_port": 0,
    "signature_length": 26,
    "signature_word_count": 3,
    "threat_malware": 0,
    "threat_exploit": 0,
    "threat_scan": 0,
    "threat_dos": 0,
    "threat_botnet": 0,
    "threat_suspicious": 0,
    "flow_direction": ""
  },
  {
    "alert_id": 0,
    "timestamp": 1764762646.282856,
    "signature_text": "SURICATA Ethertype unknown",
    "category_text": "Generic Protocol Command Decode",
    "src_ip": "",
    "dest_ip": "",
    "proto": "",
    "app_proto": "",
    "src_port": 0,
    "dest_port": 0,
    "signature_length": 26,
    "signature_word_count": 3,
    "threat_malware": 0,
    "threat_exploit": 0,
    "threat_scan": 0,
    "threat_dos": 0,
    "threat_botnet": 0,
    "threat_suspicious": 0,
    "flow_direction": ""
  },
  {
    "alert_id": 0,
    "timestamp": 1764762647.285316,
    "signature_text": "SURICATA Ethertype unknown",
    "category_text": "Generic Protocol Command Decode",
    "src_ip": "",
    "dest_ip": "",
    "proto": "",
    "app_proto": "",
    "src_port": 0,
    "dest_port": 0,
    "signature_length": 26,
    "signature_word_count": 3,
    "threat_malware": 0,
    "threat_exploit": 0,
    "threat_scan": 0,
    "threat_dos": 0,
    "threat_botnet": 0,
    "threat_suspicious": 0,
    "flow_direction": ""
  },
  {
    "alert_id": 0,
    "timestamp": 1764762648.790511,
    "signature_text": "SURICATA Ethertype unknown",
    "category_text": "Generic Protocol Command Decode",
    "src_ip": "",
    "dest_ip": "",
    "proto": "",
    "app_proto": "",
    "src_port": 0,
    "dest_port": 0,
    "signature_length": 26,
    "signature_word_count": 3,
    "threat_malware": 0,
    "threat_exploit": 0,
    "threat_scan": 0,
    "threat_dos": 0,
    "threat_botnet": 0,
    "threat_suspicious": 0,
    "flow_direction": ""
  },
  {
    "alert_id": 75575697637118,
    "timestamp": 1764762649.717361,
    "signature_text": "SURICATA STREAM excessive retransmissions",
    "category_text": "Generic Protocol Command Decode",
    "src_ip": "149.154.167.151",
    "dest_ip": "10.80.9.61",
    "proto": "TCP",
    "app_proto": "failed",
    "src_port": 443,
    "dest_port": 62944,
    "signature_length": 41,
    "signature_word_count": 4,
    "threat_malware": 0,
    "threat_exploit": 0,
    "threat_scan": 0,
    "threat_dos": 0,
    "threat_botnet": 0,
    "threat_suspicious": 0,
    "flow_direction": "to_client"
  },
  {
    "alert_id": 0,
    "timestamp": 1764762650.06387,
    "signature_text": "SURICATA Ethertype unknown",
    "category_text": "Generic Protocol Command Decode",
    "src_ip": "",
    "dest_ip": "",
    "proto": "",
    "app_proto": "",
    "src_port": 0,
    "dest_port": 0,
    "signature_length": 26,
    "signature_word_count": 3,
    "threat_malware": 0,
    "threat_exploit": 0,
    "threat_scan": 0,
    "threat_dos": 0,
    "threat_botnet": 0,
    "threat_suspicious": 0,
    "flow_direction": ""
  },
  {
    "alert_id": 0,
    "timestamp": 1764762650.790825,
    "signature_text": "SURICATA Ethertype unknown",
    "category_text": "Generic Protocol Command Decode",
    "src_ip": "",
    "dest_ip": "",
    "proto": "",
    "app_proto": "",
    "src_port": 0,
    "dest_port": 0,
    "signature_length": 26,
    "signature_word_count": 3,
    "threat_malware": 0,
    "threat_exploit": 0,
    "threat_scan": 0,
    "threat_dos": 0,
    "threat_botnet": 0,
    "threat_suspicious": 0,
    "flow_direction": ""
  },
  {
    "alert_id": 0,
    "timestamp": 1764762652.794619,
    "signature_text": "SURICATA Ethertype unknown",
    "category_text": "Generic Protocol Command Decode",
    "src_ip": "",
    "dest_ip": "",
    "proto": "",
    "app_proto": "",
    "src_port": 0,
    "dest_port": 0,
    "signature_length": 26,
    "signature_word_count": 3,
    "threat_malware": 0,
    "threat_exploit": 0,
    "threat_scan": 0,
    "threat_dos": 0,
    "threat_botnet": 0,
    "threat_suspicious": 0,
    "flow_direction": ""
  },
  {
    "alert_id": 905665721463201,
    "timestamp": 1764762652.86064,
    "signature_text": "SURICATA STREAM excessive retransmissions",
    "category_text": "Generic Protocol Command Decode",
    "src_ip": "149.154.167.151",
    "dest_ip": "10.80.9.61",
    "proto": "TCP",
    "app_proto": "failed",
    "src_port": 443,
    "dest_port": 62945,
    "signature_length": 41,
    "signature_word_count": 4,
    "threat_malware": 0,
    "threat_exploit": 0,
    "threat_scan": 0,
    "threat_dos": 0,
    "threat_botnet": 0,
    "threat_suspicious": 0,
    "flow_direction": "to_client"
  },
  {
    "alert_id": 1321725039608037,
    "timestamp": 1764762654.433905,
    "signature_text": "SURICATA STREAM excessive retransmissions",
    "category_text": "Generic Protocol Command Decode",
    "src_ip": "149.154.167.151",
    "dest_ip": "10.80.9.61",
    "proto": "TCP",
    "app_proto": "failed",
    "src_port": 443,
    "dest_port": 62946,
    "signature_length": 41,
    "signature_word_count": 4,
    "threat_malware": 0,
    "threat_exploit": 0,
    "threat_scan": 0,
    "threat_dos": 0,
    "threat_botnet": 0,
    "threat_suspicious": 0,
    "flow_direction": "to_client"
  },
  {
    "alert_id": 0,
    "timestamp": 1764762654.791081,
    "signature_text": "SURICATA Ethertype unknown",
    "category_text": "Generic Protocol Command Decode",
    "src_ip": "",
    "dest_ip": "",
    "proto": "",
    "app_proto": "",
    "src_port": 0,
    "dest_port": 0,
    "signature_length": 26,
    "signature_word_count": 3,
    "threat_malware": 0,
    "threat_exploit": 0,
    "threat_scan": 0,
    "threat_dos": 0,
    "threat_botnet": 0,
    "threat_suspicious": 0,
    "flow_direction": ""
  },
  {
    "alert_id": 0,
    "timestamp": 1764762656.792139,
    "signature_text": "SURICATA Ethertype unknown",
    "category_text": "Generic Protocol Command Decode",
    "src_ip": "",
    "dest_ip": "",
    "proto": "",
    "app_proto": "",
    "src_port": 0,
    "dest_port": 0,
    "signature_length": 26,
    "signature_word_count": 3,
    "threat_malware": 0,
    "threat_exploit": 0,
    "threat_scan": 0,
    "threat_dos": 0,
    "threat_botnet": 0,
    "threat_suspicious": 0,
    "flow_direction": ""
  },
  {
    "alert_id": 0,
    "timestamp": 1764762658.55265,
    "signature_text": "SURICATA Ethertype unknown",
    "category_text": "Generic Protocol Command Decode",
    "src_ip": "",
    "dest_ip": "",
    "proto": "",
    "app_proto": "",
    "src_port": 0,
    "dest_port": 0,
    "signature_length": 26,
    "signature_word_count": 3,
    "threat_malware": 0,
    "threat_exploit": 0,
    "threat_scan": 0,
    "threat_dos": 0,
    "threat_botnet": 0,
    "threat_suspicious": 0,
    "flow_direction": ""
  },
  {
    "alert_id": 0,
    "timestamp": 1764762658.552652,
    "signature_text": "SURICATA Ethertype unknown",
    "category_text": "Generic Protocol Command Decode",
    "src_ip": "",
    "dest_ip": "",
    "proto": "",
    "app_proto": "",
    "src_port": 0,
    "dest_port": 0,
    "signature_length": 26,
    "signature_word_count": 3,
    "threat_malware": 0,
    "threat_exploit": 0,
    "threat_scan": 0,
    "threat_dos": 0,
    "threat_botnet": 0,
    "threat_suspicious": 0,
    "flow_direction": ""
  },
  {
    "alert_id": 0,
    "timestamp": 1764762658.794777,
    "signature_text": "SURICATA Ethertype unknown",
    "category_text": "Generic Protocol Command Decode",
    "src_ip": "",
    "dest_ip": "",
    "proto": "",
    "app_proto": "",
    "src_port": 0,
    "dest_port": 0,
    "signature_length": 26,
    "signature_word_count": 3,
    "threat_malware": 0,
    "threat_exploit": 0,
    "threat_scan": 0,
    "threat_dos": 0,
    "threat_botnet": 0,
    "threat_suspicious": 0,
    "flow_direction": ""
  },
  {
    "alert_id": 0,
    "timestamp": 1764762660.06374,
    "signature_text": "SURICATA Ethertype unknown",
    "category_text": "Generic Protocol Command Decode",
    "src_ip": "",
    "dest_ip": "",
    "proto": "",
    "app_proto": "",
    "src_port": 0,
    "dest_port": 0,
    "signature_length": 26,
    "signature_word_count": 3,
    "threat_malware": 0,
    "threat_exploit": 0,
    "threat_scan": 0,
    "threat_dos": 0,
    "threat_botnet": 0,
    "threat_suspicious": 0,
    "flow_direction": ""
  },
  {
    "alert_id": 0,
    "timestamp": 1764762660.791019,
    "signature_text": "SURICATA Ethertype unknown",
    "category_text": "Generic Protocol Command Decode",
    "src_ip": "",
    "dest_ip": "",
    "proto": "",
    "app_proto": "",
    "src_port": 0,
    "dest_port": 0,
    "signature_length": 26,
    "signature_word_count": 3,
    "threat_malware": 0,
    "threat_exploit": 0,
    "threat_scan": 0,
    "threat_dos": 0,
    "threat_botnet": 0,
    "threat_suspicious": 0,
    "flow_direction": ""
  },
  {
    "alert_id": 0,
    "timestamp": 1764762662.790617,
    "signature_text": "SURICATA Ethertype unknown",
    "category_text": "Generic Protocol Command Decode",
    "src_ip": "",
    "dest_ip": "",
    "proto": "",
    "app_proto": "",
    "src_port": 0,
    "dest_port": 0,
    "signature_length": 26,
    "signature_word_count": 3,
    "threat_malware": 0,
    "threat_exploit": 0,
    "threat_scan": 0,
    "threat_dos": 0,
    "threat_botnet": 0,
    "threat_suspicious": 0,
    "flow_direction": ""
  },
  {
    "alert_id": 0,
    "timestamp": 1764762664.791165,
    "signature_text": "SURICATA Ethertype unknown",
    "category_text": "Generic Protocol Command Decode",
    "src_ip": "",
    "dest_ip": "",
    "proto": "",
    "app_proto": "",
    "src_port": 0,
    "dest_port": 0,
    "signature_length": 26,
    "signature_word_count": 3,
    "threat_malware": 0,
    "threat_exploit": 0,
    "threat_scan": 0,
    "threat_dos": 0,
    "threat_botnet": 0,
    "threat_suspicious": 0,
    "flow_direction": ""
  },
  {
    "alert_id": 0,
    "timestamp": 1764762666.806092,
    "signature_text": "SURICATA Ethertype unknown",
    "category_text": "Generic Protocol Command Decode",
    "src_ip": "",
    "dest_ip": "",
    "proto": "",
    "app_proto": "",
    "src_port": 0,
    "dest_port": 0,
    "signature_length": 26,
    "signature_word_count": 3,
    "threat_malware": 0,
    "threat_exploit": 0,
    "threat_scan": 0,
    "threat_dos": 0,
    "threat_botnet": 0,
    "threat_suspicious": 0,
    "flow_direction": ""
  },
  {
    "alert_id": 0,
    "timestamp": 1764762668.266909,
    "signature_text": "SURICATA Ethertype unknown",
    "category_text": "Generic Protocol Command Decode",
    "src_ip": "",
    "dest_ip": "",
    "proto": "",
    "app_proto": "",
    "src_port": 0,
    "dest_port": 0,
    "signature_length": 26,
    "signature_word_count": 3,
    "threat_malware": 0,
    "threat_exploit": 0,
    "threat_scan": 0,
    "threat_dos": 0,
    "threat_botnet": 0,
    "threat_suspicious": 0,
    "flow_direction": ""
  },
  {
    "alert_id": 0,
    "timestamp": 1764762669.266458,
    "signature_text": "SURICATA Ethertype unknown",
    "category_text": "Generic Protocol Command Decode",
    "src_ip": "",
    "dest_ip": "",
    "proto": "",
    "app_proto": "",
    "src_port": 0,
    "dest_port": 0,
    "signature_length": 26,
    "signature_word_count": 3,
    "threat_malware": 0,
    "threat_exploit": 0,
    "threat_scan": 0,
    "threat_dos": 0,
    "threat_botnet": 0,
    "threat_suspicious": 0,
    "flow_direction": ""
  },
  {
    "alert_id": 0,
    "timestamp": 1764762670.063949,
    "signature_text": "SURICATA Ethertype unknown",
    "category_text": "Generic Protocol Command Decode",
    "src_ip": "",
    "dest_ip": "",
    "proto": "",
    "app_proto": "",
    "src_port": 0,
    "dest_port": 0,
    "signature_length": 26,
    "signature_word_count": 3,
    "threat_malware": 0,
    "threat_exploit": 0,
    "threat_scan": 0,
    "threat_dos": 0,
    "threat_botnet": 0,
    "threat_suspicious": 0,
    "flow_direction": ""
  },
  {
    "alert_id": 0,
    "timestamp": 1764762670.269945,
    "signature_text": "SURICATA Ethertype unknown",
    "category_text": "Generic Protocol Command Decode",
    "src_ip": "",
    "dest_ip": "",
    "proto": "",
    "app_proto": "",
    "src_port": 0,
    "dest_port": 0,
    "signature_length": 26,
    "signature_word_count": 3,
    "threat_malware": 0,
    "threat_exploit": 0,
    "threat_scan": 0,
    "threat_dos": 0,
    "threat_botnet": 0,
    "threat_suspicious": 0,
    "flow_direction": ""
  },
  {
    "alert_id": 0,
    "timestamp": 1764762671.794885,
    "signature_text": "SURICATA Ethertype unknown",
    "category_text": "Generic Protocol Command Decode",
    "src_ip": "",
    "dest_ip": "",
    "proto": "",
    "app_proto": "",
    "src_port": 0,
    "dest_port": 0,
    "signature_length": 26,
    "signature_word_count": 3,
    "threat_malware": 0,
    "threat_exploit": 0,
    "threat_scan": 0,
    "threat_dos": 0,
    "threat_botnet": 0,
    "threat_suspicious": 0,
    "flow_direction": ""
  },
  {
    "alert_id": 0,
    "timestamp": 1764762673.790921,
    "signature_text": "SURICATA Ethertype unknown",
    "category_text": "Generic Protocol Command Decode",
    "src_ip": "",
    "dest_ip": "",
    "proto": "",
    "app_proto": "",
    "src_port": 0,
    "dest_port": 0,
    "signature_length": 26,
    "signature_word_count": 3,
    "threat_malware": 0,
    "threat_exploit": 0,
    "threat_scan": 0,
    "threat_dos": 0,
    "threat_botnet": 0,
    "threat_suspicious": 0,
    "flow_direction": ""
  },
  {
    "alert_id": 728095957494247,
    "timestamp": 1764762674.176175,
    "signature_text": "ET INFO Windows Update P2P Activity",
    "category_text": "Not Suspicious Traffic",
    "src_ip": "10.80.9.61",
    "dest_ip": "10.61.3.231",
    "proto": "TCP",
    "app_proto": "",
    "src_port": 54008,
    "dest_port": 7680,
    "signature_length": 35,
    "signature_word_count": 6,
    "threat_malware": 0,
    "threat_exploit": 0,
    "threat_scan": 0,
    "threat_dos": 0,
    "threat_botnet": 0,
    "threat_suspicious": 0,
    "flow_direction": "to_server"
  },
  {
    "alert_id": 2188514734648318,
    "timestamp": 1764762675.2711,
    "signature_text": "GPL ATTACK_RESPONSE id check returned root",
    "category_text": "Potentially Bad Traffic",
    "src_ip": "18.66.122.21",
    "dest_ip": "10.80.10.147",
    "proto": "TCP",
    "app_proto": "http",
    "src_port": 80,
    "dest_port": 56270,
    "signature_length": 42,
    "signature_word_count": 6,
    "threat_malware": 0,
    "threat_exploit": 0,
    "threat_scan": 0,
    "threat_dos": 0,
    "threat_botnet": 0,
    "threat_suspicious": 0,
    "flow_direction": "to_client"
  },
  {
    "alert_id": 0,
    "timestamp": 1764762675.794419,
    "signature_text": "SURICATA Ethertype unknown",
    "category_text": "Generic Protocol Command Decode",
    "src_ip": "",
    "dest_ip": "",
    "proto": "",
    "app_proto": "",
    "src_port": 0,
    "dest_port": 0,
    "signature_length": 26,
    "signature_word_count": 3,
    "threat_malware": 0,
    "threat_exploit": 0,
    "threat_scan": 0,
    "threat_dos": 0,
    "threat_botnet": 0,
    "threat_suspicious": 0,
    "flow_direction": ""
  },
  {
    "alert_id": 0,
    "timestamp": 1764762677.791289,
    "signature_text": "SURICATA Ethertype unknown",
    "category_text": "Generic Protocol Command Decode",
    "src_ip": "",
    "dest_ip": "",
    "proto": "",
    "app_proto": "",
    "src_port": 0,
    "dest_port": 0,
    "signature_length": 26,
    "signature_word_count": 3,
    "threat_malware": 0,
    "threat_exploit": 0,
    "threat_scan": 0,
    "threat_dos": 0,
    "threat_botnet": 0,
    "threat_suspicious": 0,
    "flow_direction": ""
  },
  {
    "alert_id": 0,
    "timestamp": 1764762679.791242,
    "signature_text": "SURICATA Ethertype unknown",
    "category_text": "Generic Protocol Command Decode",
    "src_ip": "",
    "dest_ip": "",
    "proto": "",
    "app_proto": "",
    "src_port": 0,
    "dest_port": 0,
    "signature_length": 26,
    "signature_word_count": 3,
    "threat_malware": 0,
    "threat_exploit": 0,
    "threat_scan": 0,
    "threat_dos": 0,
    "threat_botnet": 0,
    "threat_suspicious": 0,
    "flow_direction": ""
  },
  {
    "alert_id": 0,
    "timestamp": 1764762680.104263,
    "signature_text": "SURICATA Ethertype unknown",
    "category_text": "Generic Protocol Command Decode",
    "src_ip": "",
    "dest_ip": "",
    "proto": "",
    "app_proto": "",
    "src_port": 0,
    "dest_port": 0,
    "signature_length": 26,
    "signature_word_count": 3,
    "threat_malware": 0,
    "threat_exploit": 0,
    "threat_scan": 0,
    "threat_dos": 0,
    "threat_botnet": 0,
    "threat_suspicious": 0,
    "flow_direction": ""
  },
  {
    "alert_id": 0,
    "timestamp": 1764762681.793303,
    "signature_text": "SURICATA Ethertype unknown",
    "category_text": "Generic Protocol Command Decode",
    "src_ip": "",
    "dest_ip": "",
    "proto": "",
    "app_proto": "",
    "src_port": 0,
    "dest_port": 0,
    "signature_length": 26,
    "signature_word_count": 3,
    "threat_malware": 0,
    "threat_exploit": 0,
    "threat_scan": 0,
    "threat_dos": 0,
    "threat_botnet": 0,
    "threat_suspicious": 0,
    "flow_direction": ""
  },
  {
    "alert_id": 0,
    "timestamp": 1764762682.79015,
    "signature_text": "SURICATA Ethertype unknown",
    "category_text": "Generic Protocol Command Decode",
    "src_ip": "",
    "dest_ip": "",
    "proto": "",
    "app_proto": "",
    "src_port": 0,
    "dest_port": 0,
    "signature_length": 26,
    "signature_word_count": 3,
    "threat_malware": 0,
    "threat_exploit": 0,
    "threat_scan": 0,
    "threat_dos": 0,
    "threat_botnet": 0,
    "threat_suspicious": 0,
    "flow_direction": ""
  },
  {
    "alert_id": 0,
    "timestamp": 1764762683.795114,
    "signature_text": "SURICATA Ethertype unknown",
    "category_text": "Generic Protocol Command Decode",
    "src_ip": "",
    "dest_ip": "",
    "proto": "",
    "app_proto": "",
    "src_port": 0,
    "dest_port": 0,
    "signature_length": 26,
    "signature_word_count": 3,
    "threat_malware": 0,
    "threat_exploit": 0,
    "threat_scan": 0,
    "threat_dos": 0,
    "threat_botnet": 0,
    "threat_suspicious": 0,
    "flow_direction": ""
  },
  {
    "alert_id": 0,
    "timestamp": 1764762685.790942,
    "signature_text": "SURICATA Ethertype unknown",
    "category_text": "Generic Protocol Command Decode",
    "src_ip": "",
    "dest_ip": "",
    "proto": "",
    "app_proto": "",
    "src_port": 0,
    "dest_port": 0,
    "signature_length": 26,
    "signature_word_count": 3,
    "threat_malware": 0,
    "threat_exploit": 0,
    "threat_scan": 0,
    "threat_dos": 0,
    "threat_botnet": 0,
    "threat_suspicious": 0,
    "flow_direction": ""
  },
  {
    "alert_id": 0,
    "timestamp": 1764762687.791439,
    "signature_text": "SURICATA Ethertype unknown",
    "category_text": "Generic Protocol Command Decode",
    "src_ip": "",
    "dest_ip": "",
    "proto": "",
    "app_proto": "",
    "src_port": 0,
    "dest_port": 0,
    "signature_length": 26,
    "signature_word_count": 3,
    "threat_malware": 0,
    "threat_exploit": 0,
    "threat_scan": 0,
    "threat_dos": 0,
    "threat_botnet": 0,
    "threat_suspicious": 0,
    "flow_direction": ""
  },
  {
    "alert_id": 0,
    "timestamp": 1764762688.553602,
    "signature_text": "SURICATA Ethertype unknown",
    "category_text": "Generic Protocol Command Decode",
    "src_ip": "",
    "dest_ip": "",
    "proto": "",
    "app_proto": "",
    "src_port": 0,
    "dest_port": 0,
    "signature_length": 26,
    "signature_word_count": 3,
    "threat_malware": 0,
    "threat_exploit": 0,
    "threat_scan": 0,
    "threat_dos": 0,
    "threat_botnet": 0,
    "threat_suspicious": 0,
    "flow_direction": ""
  },
  {
    "alert_id": 0,
    "timestamp": 1764762688.553609,
    "signature_text": "SURICATA Ethertype unknown",
    "category_text": "Generic Protocol Command Decode",
    "src_ip": "",
    "dest_ip": "",
    "proto": "",
    "app_proto": "",
    "src_port": 0,
    "dest_port": 0,
    "signature_length": 26,
    "signature_word_count": 3,
    "threat_malware": 0,
    "threat_exploit": 0,
    "threat_scan": 0,
    "threat_dos": 0,
    "threat_botnet": 0,
    "threat_suspicious": 0,
    "flow_direction": ""
  }
]